{
  "legislative_session": "34",
  "identifier": "HJR13",
  "title": "Urging the President of the United States to expand evacuation efforts for applicants with approved Special Immigrant Visas, including resumption of evacuation flights organized by the Coordinator for Afghan Relocation Efforts; urging the United States Department of State to secure legal protections and humanitarian assistance for Special Immigrant Visa applicants; urging the United States Citizenship and Immigration Services in the United States Department of Homeland Security to expedite the review of applications for Special Immigrant Visas; and requesting that the United States Secretary of State provide a report to Congress regarding efforts to reinstate evacuation flights for applicants with approved Special Immigrant Visas.",
  "from_organization": "~{\"classification\": \"lower\"}",
  "classification": [
    "joint resolution"
  ],
  "subject": [
    "ALIENS",
    "INTERGOVERNMENTAL RELATIONS",
    "MILITARY",
    "RESIDENCY",
    "TERRORISM",
    "WARFARE"
  ],
  "abstracts": [],
  "other_titles": [],
  "other_identifiers": [],
  "actions": [
    {
      "description": "(H) READ THE FIRST TIME - REFERRALS",
      "date": "2025-03-21",
      "organization_id": "~{\"classification\": \"lower\"}",
      "classification": [
        "reading-1"
      ],
      "related_entities": [],
      "_processing": {
        "log_file_created": "2025-10-23T17:44:30Z"
      }
    },
    {
      "description": "(H) MLV",
      "date": "2025-03-21",
      "organization_id": "~{\"classification\": \"lower\"}",
      "classification": [],
      "related_entities": [],
      "_processing": {
        "log_file_created": "2025-10-23T17:44:30Z"
      }
    },
    {
      "description": "(H) MILITARY & VETERANS' AFFAIRS at 10:15 AM BARNES 124",
      "date": "2025-04-08",
      "organization_id": "~{\"classification\": \"lower\"}",
      "classification": [],
      "related_entities": [],
      "_processing": {
        "log_file_created": "2025-10-23T17:44:30Z"
      }
    },
    {
      "description": "(H) Heard & Held",
      "date": "2025-04-08",
      "organization_id": "~{\"classification\": \"lower\"}",
      "classification": [],
      "related_entities": [],
      "_processing": {
        "log_file_created": "2025-10-23T17:44:30Z"
      }
    },
    {
      "description": "(H) COSPONSOR(S): HALL, ALLARD",
      "date": "2025-04-09",
      "organization_id": "~{\"classification\": \"lower\"}",
      "classification": [],
      "related_entities": [],
      "_processing": {
        "log_file_created": "2025-10-23T17:44:30Z"
      }
    },
    {
      "description": "(H) MILITARY & VETERANS' AFFAIRS at 10:15 AM BARNES 124",
      "date": "2025-04-15",
      "organization_id": "~{\"classification\": \"lower\"}",
      "classification": [],
      "related_entities": [],
      "_processing": {
        "log_file_created": "2025-10-23T17:44:30Z"
      }
    },
    {
      "description": "(H) -- MEETING CANCELED --",
      "date": "2025-04-15",
      "organization_id": "~{\"classification\": \"lower\"}",
      "classification": [],
      "related_entities": [],
      "_processing": {
        "log_file_created": "2025-10-23T17:44:30Z"
      }
    },
    {
      "description": "(H) MILITARY & VETERANS' AFFAIRS at 10:15 AM BARNES 124",
      "date": "2025-04-24",
      "organization_id": "~{\"classification\": \"lower\"}",
      "classification": [],
      "related_entities": [],
      "_processing": {
        "log_file_created": "2025-10-23T17:44:30Z"
      }
    },
    {
      "description": "(H) -- Public Testimony -- -- MEETING CANCELED --",
      "date": "2025-04-24",
      "organization_id": "~{\"classification\": \"lower\"}",
      "classification": [],
      "related_entities": [],
      "_processing": {
        "log_file_created": "2025-10-23T17:44:30Z"
      }
    },
    {
      "description": "(H) MILITARY & VETERANS' AFFAIRS at 10:15 AM BARNES 124",
      "date": "2025-04-29",
      "organization_id": "~{\"classification\": \"lower\"}",
      "classification": [],
      "related_entities": [],
      "_processing": {
        "log_file_created": "2025-10-23T17:44:30Z"
      }
    },
    {
      "description": "(H) Moved CSHJR 13(MLV) Out of Committee",
      "date": "2025-04-29",
      "organization_id": "~{\"classification\": \"lower\"}",
      "classification": [],
      "related_entities": [],
      "_processing": {
        "log_file_created": "2025-10-23T17:44:30Z"
      }
    },
    {
      "description": "(H) MLV RPT CS(MLV) NEW TITLE 4DP",
      "date": "2025-04-30",
      "organization_id": "~{\"classification\": \"lower\"}",
      "classification": [],
      "related_entities": [],
      "_processing": {
        "log_file_created": "2025-10-23T17:44:30Z"
      }
    },
    {
      "description": "(H) DP: HALL, GRAY, FIELDS, EISCHEID",
      "date": "2025-04-30",
      "organization_id": "~{\"classification\": \"lower\"}",
      "classification": [],
      "related_entities": [],
      "_processing": {
        "log_file_created": "2025-10-23T17:44:30Z"
      }
    },
    {
      "description": "(H) FN1: ZERO(LEG)",
      "date": "2025-04-30",
      "organization_id": "~{\"classification\": \"lower\"}",
      "classification": [],
      "related_entities": [],
      "_processing": {
        "log_file_created": "2025-10-23T17:44:30Z"
      }
    },
    {
      "description": "(H) RULES TO CALENDAR 5/7/2025",
      "date": "2025-05-07",
      "organization_id": "~{\"classification\": \"lower\"}",
      "classification": [],
      "related_entities": [],
      "_processing": {
        "log_file_created": "2025-10-23T17:44:30Z"
      }
    },
    {
      "description": "(H) READ THE SECOND TIME",
      "date": "2025-05-07",
      "organization_id": "~{\"classification\": \"lower\"}",
      "classification": [
        "reading-2"
      ],
      "related_entities": [],
      "_processing": {
        "log_file_created": "2025-10-23T17:44:30Z"
      }
    },
    {
      "description": "(H) MLV CS ADOPTED UC",
      "date": "2025-05-07",
      "organization_id": "~{\"classification\": \"lower\"}",
      "classification": [],
      "related_entities": [],
      "_processing": {
        "log_file_created": "2025-10-23T17:44:30Z"
      }
    },
    {
      "description": "(H) ADVANCED TO THIRD READING UC",
      "date": "2025-05-07",
      "organization_id": "~{\"classification\": \"lower\"}",
      "classification": [
        "reading-3"
      ],
      "related_entities": [],
      "_processing": {
        "log_file_created": "2025-10-23T17:44:30Z"
      }
    },
    {
      "description": "(H) READ THE THIRD TIME CSHJR 13(MLV)",
      "date": "2025-05-07",
      "organization_id": "~{\"classification\": \"lower\"}",
      "classification": [
        "reading-3"
      ],
      "related_entities": [],
      "_processing": {
        "log_file_created": "2025-10-23T17:44:30Z"
      }
    },
    {
      "description": "(H) PASSED Y40",
      "date": "2025-05-07",
      "organization_id": "~{\"classification\": \"lower\"}",
      "classification": [
        "passage"
      ],
      "related_entities": [],
      "_processing": {
        "log_file_created": "2025-10-23T17:44:30Z"
      }
    },
    {
      "description": "(H) COSPONSOR(S): JOSEPHSON, GRAY, STORY, BYNUM, MINA, KOPP",
      "date": "2025-05-07",
      "organization_id": "~{\"classification\": \"lower\"}",
      "classification": [],
      "related_entities": [],
      "_processing": {
        "log_file_created": "2025-10-23T17:44:30Z"
      }
    },
    {
      "description": "(H) TRANSMITTED TO (S)",
      "date": "2025-05-07",
      "organization_id": "~{\"classification\": \"lower\"}",
      "classification": [
        "passage"
      ],
      "related_entities": [],
      "_processing": {
        "log_file_created": "2025-10-23T17:44:30Z"
      }
    },
    {
      "description": "(H) VERSION: CSHJR 13(MLV)",
      "date": "2025-05-07",
      "organization_id": "~{\"classification\": \"lower\"}",
      "classification": [],
      "related_entities": [],
      "_processing": {
        "log_file_created": "2025-10-23T17:44:30Z"
      }
    },
    {
      "description": "(S) READ THE FIRST TIME - REFERRALS",
      "date": "2025-05-09",
      "organization_id": "~{\"classification\": \"upper\"}",
      "classification": [
        "reading-1"
      ],
      "related_entities": [],
      "_processing": {
        "log_file_created": "2025-10-23T17:44:30Z"
      }
    },
    {
      "description": "(S) STA",
      "date": "2025-05-09",
      "organization_id": "~{\"classification\": \"upper\"}",
      "classification": [],
      "related_entities": [],
      "_processing": {
        "log_file_created": "2025-10-23T17:44:30Z"
      }
    },
    {
      "description": "(S) STATE AFFAIRS at 03:30 PM BELTZ 105 (TSBldg)",
      "date": "2025-05-15",
      "organization_id": "~{\"classification\": \"upper\"}",
      "classification": [],
      "related_entities": [],
      "_processing": {
        "log_file_created": "2025-10-23T17:44:30Z"
      }
    },
    {
      "description": "(S) Heard & Held",
      "date": "2025-05-15",
      "organization_id": "~{\"classification\": \"upper\"}",
      "classification": [],
      "related_entities": [],
      "_processing": {
        "log_file_created": "2025-10-23T17:44:30Z"
      }
    },
    {
      "description": "(S) Minutes (SSTA)",
      "date": "2025-05-15",
      "organization_id": "~{\"classification\": \"upper\"}",
      "classification": [],
      "related_entities": [],
      "_processing": {
        "log_file_created": "2025-10-23T17:44:30Z"
      }
    },
    {
      "description": "(S) STA RPT 3DP 1NR",
      "date": "2025-05-17",
      "organization_id": "~{\"classification\": \"upper\"}",
      "classification": [],
      "related_entities": [],
      "_processing": {
        "log_file_created": "2025-10-23T17:44:30Z"
      }
    },
    {
      "description": "(S) DP: KAWASAKI, GRAY-JACKSON, BJORKMAN",
      "date": "2025-05-17",
      "organization_id": "~{\"classification\": \"upper\"}",
      "classification": [],
      "related_entities": [],
      "_processing": {
        "log_file_created": "2025-10-23T17:44:30Z"
      }
    },
    {
      "description": "(S) NR: WIELECHOWSKI",
      "date": "2025-05-17",
      "organization_id": "~{\"classification\": \"upper\"}",
      "classification": [],
      "related_entities": [],
      "_processing": {
        "log_file_created": "2025-10-23T17:44:30Z"
      }
    },
    {
      "description": "(S) FN1: ZERO(LEG)",
      "date": "2025-05-17",
      "organization_id": "~{\"classification\": \"upper\"}",
      "classification": [],
      "related_entities": [],
      "_processing": {
        "log_file_created": "2025-10-23T17:44:30Z"
      }
    },
    {
      "description": "(S) CROSS SPONSOR(S): KAWASAKI",
      "date": "2025-05-17",
      "organization_id": "~{\"classification\": \"upper\"}",
      "classification": [],
      "related_entities": [],
      "_processing": {
        "log_file_created": "2025-10-23T17:44:30Z"
      }
    },
    {
      "description": "(S) STATE AFFAIRS at 10:00 AM BELTZ 105 (TSBldg)",
      "date": "2025-05-17",
      "organization_id": "~{\"classification\": \"upper\"}",
      "classification": [],
      "related_entities": [],
      "_processing": {
        "log_file_created": "2025-10-23T17:44:30Z"
      }
    },
    {
      "description": "(S) Moved CSHJR 13(MLV) Out of Committee",
      "date": "2025-05-17",
      "organization_id": "~{\"classification\": \"upper\"}",
      "classification": [],
      "related_entities": [],
      "_processing": {
        "log_file_created": "2025-10-23T17:44:30Z"
      }
    },
    {
      "description": "(S) Minutes (SSTA)",
      "date": "2025-05-17",
      "organization_id": "~{\"classification\": \"upper\"}",
      "classification": [],
      "related_entities": [],
      "_processing": {
        "log_file_created": "2025-10-23T17:44:30Z"
      }
    },
    {
      "description": "(S) RULES TO CALENDAR 5/19/2025",
      "date": "2025-05-19",
      "organization_id": "~{\"classification\": \"upper\"}",
      "classification": [],
      "related_entities": [],
      "_processing": {
        "log_file_created": "2025-10-23T17:44:30Z"
      }
    },
    {
      "description": "(S) READ THE SECOND TIME",
      "date": "2025-05-19",
      "organization_id": "~{\"classification\": \"upper\"}",
      "classification": [
        "reading-2"
      ],
      "related_entities": [],
      "_processing": {
        "log_file_created": "2025-10-23T17:44:30Z"
      }
    },
    {
      "description": "(S) ADVANCED TO THIRD READING 5/20 CAL",
      "date": "2025-05-19",
      "organization_id": "~{\"classification\": \"upper\"}",
      "classification": [
        "reading-3"
      ],
      "related_entities": [],
      "_processing": {
        "log_file_created": "2025-10-23T17:44:30Z"
      }
    },
    {
      "description": "(S) READ THE THIRD TIME CSHJR 13(MLV)",
      "date": "2025-05-20",
      "organization_id": "~{\"classification\": \"upper\"}",
      "classification": [
        "reading-3"
      ],
      "related_entities": [],
      "_processing": {
        "log_file_created": "2025-10-23T17:44:30Z"
      }
    },
    {
      "description": "(S) CROSS SPONSOR(S): TOBIN, DUNBAR, SHOWER, MERRICK, BJORKMAN, YUNDT, CLAMAN,",
      "date": "2025-05-20",
      "organization_id": "~{\"classification\": \"upper\"}",
      "classification": [],
      "related_entities": [],
      "_processing": {
        "log_file_created": "2025-10-23T17:44:30Z"
      }
    },
    {
      "description": "(S) KAUFMAN, MYERS, STEDMAN, CRONK",
      "date": "2025-05-20",
      "organization_id": "~{\"classification\": \"upper\"}",
      "classification": [],
      "related_entities": [],
      "_processing": {
        "log_file_created": "2025-10-23T17:44:30Z"
      }
    },
    {
      "description": "(S) PASSED Y20 N-",
      "date": "2025-05-20",
      "organization_id": "~{\"classification\": \"upper\"}",
      "classification": [
        "passage"
      ],
      "related_entities": [],
      "_processing": {
        "log_file_created": "2025-10-23T17:44:30Z"
      }
    },
    {
      "description": "(S) RETURN TO (H), TRANSMIT TO GOV NEXT",
      "date": "2025-05-20",
      "organization_id": "~{\"classification\": \"upper\"}",
      "classification": [],
      "related_entities": [],
      "_processing": {
        "log_file_created": "2025-10-23T17:44:30Z"
      }
    },
    {
      "description": "(S) VERSION: CSHJR 13(MLV)",
      "date": "2025-05-20",
      "organization_id": "~{\"classification\": \"upper\"}",
      "classification": [],
      "related_entities": [],
      "_processing": {
        "log_file_created": "2025-10-23T17:44:30Z"
      }
    },
    {
      "description": "(H) 12:05 P.M. 6/17/25 Transmitted to Governor",
      "date": "2025-07-30",
      "organization_id": "~{\"classification\": \"lower\"}",
      "classification": [
        "executive-receipt"
      ],
      "related_entities": [],
      "_processing": {
        "log_file_created": "2025-10-23T17:44:30Z"
      }
    },
    {
      "description": "(H) MANIFEST ERROR(S)",
      "date": "2025-07-30",
      "organization_id": "~{\"classification\": \"lower\"}",
      "classification": [],
      "related_entities": [],
      "_processing": {
        "log_file_created": "2025-10-23T17:44:30Z"
      }
    },
    {
      "description": "(H) PERMANENTLY FILED 7/16 LEGIS RESOLVE 15",
      "date": "2025-07-30",
      "organization_id": "~{\"classification\": \"lower\"}",
      "classification": [],
      "related_entities": [],
      "_processing": {
        "log_file_created": "2025-10-23T17:44:30Z"
      }
    }
  ],
  "sponsorships": [
    {
      "name": "Stapp",
      "classification": "primary",
      "entity_type": "person",
      "primary": true,
      "person_id": "~{\"chamber\": \"lower\", \"name\": \"Stapp\"}",
      "organization_id": null
    },
    {
      "name": "Saddler",
      "classification": "cosponsor",
      "entity_type": "person",
      "primary": false,
      "person_id": "~{\"chamber\": \"lower\", \"name\": \"Saddler\"}",
      "organization_id": null
    },
    {
      "name": "Eischeid",
      "classification": "cosponsor",
      "entity_type": "person",
      "primary": false,
      "person_id": "~{\"chamber\": \"lower\", \"name\": \"Eischeid\"}",
      "organization_id": null
    },
    {
      "name": "Fields",
      "classification": "cosponsor",
      "entity_type": "person",
      "primary": false,
      "person_id": "~{\"chamber\": \"lower\", \"name\": \"Fields\"}",
      "organization_id": null
    },
    {
      "name": "Hannan",
      "classification": "cosponsor",
      "entity_type": "person",
      "primary": false,
      "person_id": "~{\"chamber\": \"lower\", \"name\": \"Hannan\"}",
      "organization_id": null
    },
    {
      "name": "Hall",
      "classification": "cosponsor",
      "entity_type": "person",
      "primary": false,
      "person_id": "~{\"chamber\": \"lower\", \"name\": \"Hall\"}",
      "organization_id": null
    },
    {
      "name": "Allard",
      "classification": "cosponsor",
      "entity_type": "person",
      "primary": false,
      "person_id": "~{\"chamber\": \"lower\", \"name\": \"Allard\"}",
      "organization_id": null
    },
    {
      "name": "Josephson",
      "classification": "cosponsor",
      "entity_type": "person",
      "primary": false,
      "person_id": "~{\"chamber\": \"lower\", \"name\": \"Josephson\"}",
      "organization_id": null
    },
    {
      "name": "Gray",
      "classification": "cosponsor",
      "entity_type": "person",
      "primary": false,
      "person_id": "~{\"chamber\": \"lower\", \"name\": \"Gray\"}",
      "organization_id": null
    },
    {
      "name": "Story",
      "classification": "cosponsor",
      "entity_type": "person",
      "primary": false,
      "person_id": "~{\"chamber\": \"lower\", \"name\": \"Story\"}",
      "organization_id": null
    },
    {
      "name": "Bynum",
      "classification": "cosponsor",
      "entity_type": "person",
      "primary": false,
      "person_id": "~{\"chamber\": \"lower\", \"name\": \"Bynum\"}",
      "organization_id": null
    },
    {
      "name": "Mina",
      "classification": "cosponsor",
      "entity_type": "person",
      "primary": false,
      "person_id": "~{\"chamber\": \"lower\", \"name\": \"Mina\"}",
      "organization_id": null
    },
    {
      "name": "Kopp",
      "classification": "cosponsor",
      "entity_type": "person",
      "primary": false,
      "person_id": "~{\"chamber\": \"lower\", \"name\": \"Kopp\"}",
      "organization_id": null
    },
    {
      "name": "Kawasaki",
      "classification": "cosponsor",
      "entity_type": "person",
      "primary": false,
      "person_id": "~{\"chamber\": \"upper\", \"name\": \"Kawasaki\"}",
      "organization_id": null
    },
    {
      "name": "Tobin",
      "classification": "cosponsor",
      "entity_type": "person",
      "primary": false,
      "person_id": "~{\"chamber\": \"upper\", \"name\": \"Tobin\"}",
      "organization_id": null
    },
    {
      "name": "Dunbar",
      "classification": "cosponsor",
      "entity_type": "person",
      "primary": false,
      "person_id": "~{\"chamber\": \"upper\", \"name\": \"Dunbar\"}",
      "organization_id": null
    },
    {
      "name": "Shower",
      "classification": "cosponsor",
      "entity_type": "person",
      "primary": false,
      "person_id": "~{\"chamber\": \"upper\", \"name\": \"Shower\"}",
      "organization_id": null
    },
    {
      "name": "Merrick",
      "classification": "cosponsor",
      "entity_type": "person",
      "primary": false,
      "person_id": "~{\"chamber\": \"upper\", \"name\": \"Merrick\"}",
      "organization_id": null
    },
    {
      "name": "Bjorkman",
      "classification": "cosponsor",
      "entity_type": "person",
      "primary": false,
      "person_id": "~{\"chamber\": \"upper\", \"name\": \"Bjorkman\"}",
      "organization_id": null
    },
    {
      "name": "Yundt",
      "classification": "cosponsor",
      "entity_type": "person",
      "primary": false,
      "person_id": "~{\"chamber\": \"upper\", \"name\": \"Yundt\"}",
      "organization_id": null
    },
    {
      "name": "Claman",
      "classification": "cosponsor",
      "entity_type": "person",
      "primary": false,
      "person_id": "~{\"chamber\": \"upper\", \"name\": \"Claman\"}",
      "organization_id": null
    },
    {
      "name": "Kaufman",
      "classification": "cosponsor",
      "entity_type": "person",
      "primary": false,
      "person_id": "~{\"chamber\": \"upper\", \"name\": \"Kaufman\"}",
      "organization_id": null
    },
    {
      "name": "Myers",
      "classification": "cosponsor",
      "entity_type": "person",
      "primary": false,
      "person_id": "~{\"chamber\": \"upper\", \"name\": \"Myers\"}",
      "organization_id": null
    },
    {
      "name": "Stedman",
      "classification": "cosponsor",
      "entity_type": "person",
      "primary": false,
      "person_id": "~{\"chamber\": \"upper\", \"name\": \"Stedman\"}",
      "organization_id": null
    },
    {
      "name": "Cronk",
      "classification": "cosponsor",
      "entity_type": "person",
      "primary": false,
      "person_id": "~{\"chamber\": \"upper\", \"name\": \"Cronk\"}",
      "organization_id": null
    }
  ],
  "related_bills": [],
  "versions": [
    {
      "note": "HJR 13",
      "links": [
        {
          "url": "https://www.akleg.gov/basis/Bill/Text/34?Hsid=HJR013A",
          "media_type": "text/html"
        },
        {
          "url": "https://www.akleg.gov/PDF/34/Bills/HJR013A.PDF",
          "media_type": "application/pdf"
        }
      ],
      "date": "",
      "classification": ""
    },
    {
      "note": "CSHJR 13(MLV)",
      "links": [
        {
          "url": "https://www.akleg.gov/basis/Bill/Text/34?Hsid=HJR013B",
          "media_type": "text/html"
        },
        {
          "url": "https://www.akleg.gov/PDF/34/Bills/HJR013B.PDF",
          "media_type": "application/pdf"
        }
      ],
      "date": "",
      "classification": ""
    },
    {
      "note": "Enrolled HJR 13",
      "links": [
        {
          "url": "https://www.akleg.gov/basis/Bill/Text/34?Hsid=HJR013Z",
          "media_type": "text/html"
        },
        {
          "url": "https://www.akleg.gov/PDF/34/Bills/HJR013Z.PDF",
          "media_type": "application/pdf"
        }
      ],
      "date": "",
      "classification": ""
    }
  ],
  "documents": [
    {
      "note": "HJR 13 Amendment I.2",
      "links": [
        {
          "url": "https://www.akleg.gov/basis/get_documents.asp?session=34&docid=6275",
          "media_type": "pdf"
        }
      ],
      "date": "",
      "classification": ""
    },
    {
      "note": "HJR 13 Susan Allmeroth Testimony 04.15.25",
      "links": [
        {
          "url": "https://www.akleg.gov/basis/get_documents.asp?session=34&docid=5972",
          "media_type": "pdf"
        }
      ],
      "date": "",
      "classification": ""
    },
    {
      "note": "HJR 13 Sponser Statement version A",
      "links": [
        {
          "url": "https://www.akleg.gov/basis/get_documents.asp?session=34&docid=5378",
          "media_type": "pdf"
        }
      ],
      "date": "",
      "classification": ""
    },
    {
      "note": "HJR013A.DOC",
      "links": [
        {
          "url": "https://www.akleg.gov/basis/get_documents.asp?session=34&docid=5377",
          "media_type": "pdf"
        }
      ],
      "date": "",
      "classification": ""
    },
    {
      "note": "HJR13 LEG ZERO FN 04-11-2025",
      "links": [
        {
          "url": "https://www.akleg.gov/basis/get_documents.asp?session=34&docid=5376",
          "media_type": "pdf"
        }
      ],
      "date": "",
      "classification": ""
    }
  ],
  "citations": [],
  "sources": [
    {
      "url": "https://www.akleg.gov/basis/Bill/Detail/34?Root=HJR13",
      "note": ""
    },
    {
      "url": "https://www.akleg.gov/basis/Bill/Detail/34?Root=HJR13#tab5_4",
      "note": ""
    }
  ],
  "extras": {},
  "jurisdiction": {
    "id": "ocd-jurisdiction/country:us/state:ak/government",
    "name": "Alaska",
    "classification": "state",
    "division_id": "ocd-division/country:us/state:ak"
  },
  "_processing": {
    "logs_latest_update": "2025-10-23T17:44:30Z"
  }
}