{
  "legislative_session": "34",
  "identifier": "SB170",
  "title": "An Act relating to gaming; relating to bingo; relating to pull-tabs and electronic pull-tab systems; and providing for an effective date.",
  "from_organization": "~{\"classification\": \"upper\"}",
  "classification": [
    "bill"
  ],
  "subject": [
    "BUSINESS",
    "CONTRACTS",
    "GAMBLING",
    "LICENSING",
    "PERMITS",
    "REVENUE",
    "SALES",
    "TAXATION"
  ],
  "abstracts": [],
  "other_titles": [],
  "other_identifiers": [],
  "actions": [
    {
      "description": "(S) READ THE FIRST TIME - REFERRALS",
      "date": "2025-04-11",
      "organization_id": "~{\"classification\": \"upper\"}",
      "classification": [
        "reading-1"
      ],
      "related_entities": [],
      "_processing": {
        "log_file_created": "2025-10-23T17:44:31Z"
      }
    },
    {
      "description": "(S) L&C, FIN",
      "date": "2025-04-11",
      "organization_id": "~{\"classification\": \"upper\"}",
      "classification": [],
      "related_entities": [],
      "_processing": {
        "log_file_created": "2025-10-23T17:44:31Z"
      }
    },
    {
      "description": "(S) REFERRED TO LABOR & COMMERCE",
      "date": "2025-04-11",
      "organization_id": "~{\"classification\": \"upper\"}",
      "classification": [
        "referral-committee"
      ],
      "related_entities": [],
      "_processing": {
        "log_file_created": "2025-10-23T17:44:31Z"
      }
    },
    {
      "description": "(S) LABOR & COMMERCE at 01:30 PM BELTZ 105 (TSBldg)",
      "date": "2025-04-16",
      "organization_id": "~{\"classification\": \"upper\"}",
      "classification": [],
      "related_entities": [],
      "_processing": {
        "log_file_created": "2025-10-23T17:44:31Z"
      }
    },
    {
      "description": "(S) Heard & Held",
      "date": "2025-04-16",
      "organization_id": "~{\"classification\": \"upper\"}",
      "classification": [],
      "related_entities": [],
      "_processing": {
        "log_file_created": "2025-10-23T17:44:31Z"
      }
    },
    {
      "description": "(S) Minutes (SL&C)",
      "date": "2025-04-16",
      "organization_id": "~{\"classification\": \"upper\"}",
      "classification": [],
      "related_entities": [],
      "_processing": {
        "log_file_created": "2025-10-23T17:44:31Z"
      }
    },
    {
      "description": "(S) LABOR & COMMERCE at 01:30 PM BELTZ 105 (TSBldg)",
      "date": "2025-04-28",
      "organization_id": "~{\"classification\": \"upper\"}",
      "classification": [],
      "related_entities": [],
      "_processing": {
        "log_file_created": "2025-10-23T17:44:31Z"
      }
    },
    {
      "description": "(S) Heard & Held",
      "date": "2025-04-28",
      "organization_id": "~{\"classification\": \"upper\"}",
      "classification": [],
      "related_entities": [],
      "_processing": {
        "log_file_created": "2025-10-23T17:44:31Z"
      }
    },
    {
      "description": "(S) Minutes (SL&C)",
      "date": "2025-04-28",
      "organization_id": "~{\"classification\": \"upper\"}",
      "classification": [],
      "related_entities": [],
      "_processing": {
        "log_file_created": "2025-10-23T17:44:31Z"
      }
    },
    {
      "description": "(S) LABOR & COMMERCE at 01:30 PM BELTZ 105 (TSBldg)",
      "date": "2025-05-02",
      "organization_id": "~{\"classification\": \"upper\"}",
      "classification": [],
      "related_entities": [],
      "_processing": {
        "log_file_created": "2025-10-23T17:44:31Z"
      }
    },
    {
      "description": "(S) Heard & Held",
      "date": "2025-05-02",
      "organization_id": "~{\"classification\": \"upper\"}",
      "classification": [],
      "related_entities": [],
      "_processing": {
        "log_file_created": "2025-10-23T17:44:31Z"
      }
    },
    {
      "description": "(S) LABOR & COMMERCE at 01:30 PM BELTZ 105 (TSBldg)",
      "date": "2025-05-07",
      "organization_id": "~{\"classification\": \"upper\"}",
      "classification": [],
      "related_entities": [],
      "_processing": {
        "log_file_created": "2025-10-23T17:44:31Z"
      }
    },
    {
      "description": "(S) Heard & Held",
      "date": "2025-05-07",
      "organization_id": "~{\"classification\": \"upper\"}",
      "classification": [],
      "related_entities": [],
      "_processing": {
        "log_file_created": "2025-10-23T17:44:31Z"
      }
    }
  ],
  "sponsorships": [
    {
      "name": "Bjorkman",
      "classification": "primary",
      "entity_type": "person",
      "primary": true,
      "person_id": "~{\"chamber\": \"upper\", \"name\": \"Bjorkman\"}",
      "organization_id": null
    }
  ],
  "related_bills": [],
  "versions": [
    {
      "note": "SB 170",
      "links": [
        {
          "url": "https://www.akleg.gov/basis/Bill/Text/34?Hsid=SB0170A",
          "media_type": "text/html"
        },
        {
          "url": "https://www.akleg.gov/PDF/34/Bills/SB0170A.PDF",
          "media_type": "application/pdf"
        }
      ],
      "date": "",
      "classification": ""
    }
  ],
  "documents": [
    {
      "note": "Sponsor Statement",
      "links": [
        {
          "url": "http://www.akleg.gov/basis/get_documents.asp?session=34&docid=5720",
          "media_type": "pdf"
        }
      ],
      "date": "",
      "classification": ""
    },
    {
      "note": "SB170 Presentation to SLAC-AK Wholesale 05.02.25",
      "links": [
        {
          "url": "https://www.akleg.gov/basis/get_documents.asp?session=34&docid=6958",
          "media_type": "pdf"
        }
      ],
      "date": "",
      "classification": ""
    },
    {
      "note": "SB170 Public Testimony-Letter-Dave Lambert 04.28.25",
      "links": [
        {
          "url": "https://www.akleg.gov/basis/get_documents.asp?session=34&docid=6957",
          "media_type": "pdf"
        }
      ],
      "date": "",
      "classification": ""
    },
    {
      "note": "SB170 Public Testimony-Sandy Powers-Tablets Only Poll 05.01.25",
      "links": [
        {
          "url": "https://www.akleg.gov/basis/get_documents.asp?session=34&docid=6890",
          "media_type": "pdf"
        }
      ],
      "date": "",
      "classification": ""
    },
    {
      "note": "SB170 Public Testimony-Email-Dave Lambert 04.29.25",
      "links": [
        {
          "url": "https://www.akleg.gov/basis/get_documents.asp?session=34&docid=6889",
          "media_type": "pdf"
        }
      ],
      "date": "",
      "classification": ""
    },
    {
      "note": "SB170 Public Testimony-Dimond Game-Hand out- 05.01.25",
      "links": [
        {
          "url": "https://www.akleg.gov/basis/get_documents.asp?session=34&docid=6888",
          "media_type": "pdf"
        }
      ],
      "date": "",
      "classification": ""
    },
    {
      "note": "SB170 Public Testimony-Letter-Arrow Int re Constitutionality 04.14.25",
      "links": [
        {
          "url": "https://www.akleg.gov/basis/get_documents.asp?session=34&docid=6887",
          "media_type": "pdf"
        }
      ],
      "date": "",
      "classification": ""
    },
    {
      "note": "SB170 Public Testimony-Letter-Bill Breslo 04.22.25",
      "links": [
        {
          "url": "https://www.akleg.gov/basis/get_documents.asp?session=34&docid=6478",
          "media_type": "pdf"
        }
      ],
      "date": "",
      "classification": ""
    },
    {
      "note": "SB170 ver I",
      "links": [
        {
          "url": "https://www.akleg.gov/basis/get_documents.asp?session=34&docid=5721",
          "media_type": "pdf"
        }
      ],
      "date": "",
      "classification": ""
    },
    {
      "note": "SB170 Sponsor Statement ver I",
      "links": [
        {
          "url": "https://www.akleg.gov/basis/get_documents.asp?session=34&docid=5720",
          "media_type": "pdf"
        }
      ],
      "date": "",
      "classification": ""
    },
    {
      "note": "SB170 Sectional Summary ver I",
      "links": [
        {
          "url": "https://www.akleg.gov/basis/get_documents.asp?session=34&docid=5719",
          "media_type": "pdf"
        }
      ],
      "date": "",
      "classification": ""
    },
    {
      "note": "SB170 Fiscal Note DOR-TAX 04.14.25",
      "links": [
        {
          "url": "https://www.akleg.gov/basis/get_documents.asp?session=34&docid=5718",
          "media_type": "pdf"
        }
      ],
      "date": "",
      "classification": ""
    }
  ],
  "citations": [],
  "sources": [
    {
      "url": "https://www.akleg.gov/basis/Bill/Detail/34?Root=SB170",
      "note": ""
    },
    {
      "url": "https://www.akleg.gov/basis/Bill/Detail/34?Root=SB170#tab5_4",
      "note": ""
    }
  ],
  "extras": {},
  "jurisdiction": {
    "id": "ocd-jurisdiction/country:us/state:ak/government",
    "name": "Alaska",
    "classification": "state",
    "division_id": "ocd-division/country:us/state:ak"
  },
  "_processing": {
    "logs_latest_update": "2025-10-23T17:44:31Z",
    "text_extraction_latest_update": "2025-10-23T18:25:37.328173Z"
  }
}