{"identifier": "", "motion_text": "(S) PASSED Y19 N- E1 #1322", "motion_classification": ["passage"], "start_date": "2025-05-17", "result": "pass", "organization": "~{\"classification\": \"upper\"}", "legislative_session": "34", "bill": "2ac0f224-6bd7-11f0-b877-b6f2bba45fa4", "bill_action": null, "bill_identifier": "SB156", "votes": [], "counts": [{"option": "yes", "value": 19}, {"option": "no", "value": 0}, {"option": "other", "value": 1}], "sources": [{"url": "https://www.akleg.gov/basis/Journal/Pages/34?Chamber=S&Bill=SB156&Page=01322#1322", "note": ""}], "extras": {}, "_id": "2ac1611e-6bd7-11f0-b877-b6f2bba45fa4"}