{
  "legislative_session": "34",
  "identifier": "HB231",
  "title": "An Act relating to education; relating to education reports; relating to the duties of the Department of Education and Early Development; relating to teacher exit interviews conducted by school districts; relating to the teachers' retirement system; relating to the public employee retirement system; and providing for an effective date.",
  "from_organization": "~{\"classification\": \"lower\"}",
  "classification": [
    "bill"
  ],
  "subject": [
    "EMPLOYMENT",
    "OCCUPATIONS & PROFESSIONS",
    "PUBLIC EMPLOYEES",
    "RETIREMENT",
    "SCHOOL DISTRICTS",
    "SCHOOLS",
    "TEACHERS"
  ],
  "abstracts": [],
  "other_titles": [],
  "other_identifiers": [],
  "actions": [
    {
      "description": "(H) READ THE FIRST TIME - REFERRALS",
      "date": "2025-05-19",
      "organization_id": "~{\"classification\": \"lower\"}",
      "classification": [
        "reading-1"
      ],
      "related_entities": [],
      "_processing": {
        "log_file_created": "2025-10-23T17:44:30Z"
      }
    },
    {
      "description": "(H) EDC, FIN",
      "date": "2025-05-19",
      "organization_id": "~{\"classification\": \"lower\"}",
      "classification": [],
      "related_entities": [],
      "_processing": {
        "log_file_created": "2025-10-23T17:44:30Z"
      }
    },
    {
      "description": "(H) REFERRED TO EDUCATION",
      "date": "2025-05-19",
      "organization_id": "~{\"classification\": \"lower\"}",
      "classification": [
        "referral-committee"
      ],
      "related_entities": [],
      "_processing": {
        "log_file_created": "2025-10-23T17:44:30Z"
      }
    },
    {
      "description": "(H) COSPONSOR(S): HALL",
      "date": "2025-05-20",
      "organization_id": "~{\"classification\": \"lower\"}",
      "classification": [],
      "related_entities": [],
      "_processing": {
        "log_file_created": "2025-10-23T17:44:30Z"
      }
    }
  ],
  "sponsorships": [
    {
      "name": "Burke",
      "classification": "primary",
      "entity_type": "person",
      "primary": true,
      "person_id": "~{\"chamber\": \"lower\", \"name\": \"Burke\"}",
      "organization_id": null
    },
    {
      "name": "Hall",
      "classification": "cosponsor",
      "entity_type": "person",
      "primary": false,
      "person_id": "~{\"chamber\": \"lower\", \"name\": \"Hall\"}",
      "organization_id": null
    }
  ],
  "related_bills": [],
  "versions": [
    {
      "note": "HB 231",
      "links": [
        {
          "url": "https://www.akleg.gov/basis/Bill/Text/34?Hsid=HB0231A",
          "media_type": "text/html"
        },
        {
          "url": "https://www.akleg.gov/PDF/34/Bills/HB0231A.PDF",
          "media_type": "application/pdf"
        }
      ],
      "date": "",
      "classification": ""
    }
  ],
  "documents": [],
  "citations": [],
  "sources": [
    {
      "url": "https://www.akleg.gov/basis/Bill/Detail/34?Root=HB231",
      "note": ""
    },
    {
      "url": "https://www.akleg.gov/basis/Bill/Detail/34?Root=HB231#tab5_4",
      "note": ""
    }
  ],
  "extras": {},
  "jurisdiction": {
    "id": "ocd-jurisdiction/country:us/state:ak/government",
    "name": "Alaska",
    "classification": "state",
    "division_id": "ocd-division/country:us/state:ak"
  },
  "_processing": {
    "logs_latest_update": "2025-10-23T17:44:30Z"
  }
}