{
  "legislative_session": "34",
  "identifier": "SJR10",
  "title": "Encouraging the United States Congress to award Hmong veterans of the Vietnam War the Congressional Gold Medal.",
  "from_organization": "~{\"classification\": \"upper\"}",
  "classification": [
    "joint resolution"
  ],
  "subject": [
    "VETERANS"
  ],
  "abstracts": [],
  "other_titles": [],
  "other_identifiers": [],
  "actions": [
    {
      "description": "(S) READ THE FIRST TIME - REFERRALS",
      "date": "2025-02-20",
      "organization_id": "~{\"classification\": \"upper\"}",
      "classification": [
        "reading-1"
      ],
      "related_entities": [],
      "_processing": {
        "log_file_created": "2025-10-23T17:44:31Z"
      }
    },
    {
      "description": "(S) STA",
      "date": "2025-02-20",
      "organization_id": "~{\"classification\": \"upper\"}",
      "classification": [],
      "related_entities": [],
      "_processing": {
        "log_file_created": "2025-10-23T17:44:31Z"
      }
    },
    {
      "description": "(S) COSPONSOR(S): GRAY-JACKSON, KAWASAKI, DUNBAR, TOBIN",
      "date": "2025-02-24",
      "organization_id": "~{\"classification\": \"upper\"}",
      "classification": [],
      "related_entities": [],
      "_processing": {
        "log_file_created": "2025-10-23T17:44:31Z"
      }
    },
    {
      "description": "(S) STATE AFFAIRS at 03:30 PM BELTZ 105 (TSBldg)",
      "date": "2025-02-25",
      "organization_id": "~{\"classification\": \"upper\"}",
      "classification": [],
      "related_entities": [],
      "_processing": {
        "log_file_created": "2025-10-23T17:44:31Z"
      }
    },
    {
      "description": "(S) Heard & Held",
      "date": "2025-02-25",
      "organization_id": "~{\"classification\": \"upper\"}",
      "classification": [],
      "related_entities": [],
      "_processing": {
        "log_file_created": "2025-10-23T17:44:31Z"
      }
    },
    {
      "description": "(S) Minutes (SSTA)",
      "date": "2025-02-25",
      "organization_id": "~{\"classification\": \"upper\"}",
      "classification": [],
      "related_entities": [],
      "_processing": {
        "log_file_created": "2025-10-23T17:44:31Z"
      }
    },
    {
      "description": "(S) STATE AFFAIRS at 03:30 PM BELTZ 105 (TSBldg)",
      "date": "2025-03-04",
      "organization_id": "~{\"classification\": \"upper\"}",
      "classification": [],
      "related_entities": [],
      "_processing": {
        "log_file_created": "2025-10-23T17:44:31Z"
      }
    },
    {
      "description": "(S) Moved SJR 10 Out of Committee",
      "date": "2025-03-04",
      "organization_id": "~{\"classification\": \"upper\"}",
      "classification": [],
      "related_entities": [],
      "_processing": {
        "log_file_created": "2025-10-23T17:44:31Z"
      }
    },
    {
      "description": "(S) Minutes (SSTA)",
      "date": "2025-03-04",
      "organization_id": "~{\"classification\": \"upper\"}",
      "classification": [],
      "related_entities": [],
      "_processing": {
        "log_file_created": "2025-10-23T17:44:31Z"
      }
    },
    {
      "description": "(S) STA RPT 5DP",
      "date": "2025-03-05",
      "organization_id": "~{\"classification\": \"upper\"}",
      "classification": [],
      "related_entities": [],
      "_processing": {
        "log_file_created": "2025-10-23T17:44:31Z"
      }
    },
    {
      "description": "(S) DP: KAWASAKI, WIELECHOWSKI, GRAY-JACKSON, BJORKMAN, YUNDT",
      "date": "2025-03-05",
      "organization_id": "~{\"classification\": \"upper\"}",
      "classification": [],
      "related_entities": [],
      "_processing": {
        "log_file_created": "2025-10-23T17:44:31Z"
      }
    },
    {
      "description": "(S) FN1: ZERO(LEG)",
      "date": "2025-03-05",
      "organization_id": "~{\"classification\": \"upper\"}",
      "classification": [],
      "related_entities": [],
      "_processing": {
        "log_file_created": "2025-10-23T17:44:31Z"
      }
    },
    {
      "description": "(S) RULES TO CALENDAR 3/14/2025",
      "date": "2025-03-14",
      "organization_id": "~{\"classification\": \"upper\"}",
      "classification": [],
      "related_entities": [],
      "_processing": {
        "log_file_created": "2025-10-23T17:44:31Z"
      }
    },
    {
      "description": "(S) READ THE SECOND TIME",
      "date": "2025-03-14",
      "organization_id": "~{\"classification\": \"upper\"}",
      "classification": [
        "reading-2"
      ],
      "related_entities": [],
      "_processing": {
        "log_file_created": "2025-10-23T17:44:31Z"
      }
    },
    {
      "description": "(S) ADVANCED TO THIRD READING 3/17 CAL",
      "date": "2025-03-14",
      "organization_id": "~{\"classification\": \"upper\"}",
      "classification": [
        "reading-3"
      ],
      "related_entities": [],
      "_processing": {
        "log_file_created": "2025-10-23T17:44:31Z"
      }
    },
    {
      "description": "(S) READ THE THIRD TIME SJR 10",
      "date": "2025-03-17",
      "organization_id": "~{\"classification\": \"upper\"}",
      "classification": [
        "reading-3"
      ],
      "related_entities": [],
      "_processing": {
        "log_file_created": "2025-10-23T17:44:31Z"
      }
    },
    {
      "description": "(S) PASSED Y17 N- E3",
      "date": "2025-03-17",
      "organization_id": "~{\"classification\": \"upper\"}",
      "classification": [
        "passage"
      ],
      "related_entities": [],
      "_processing": {
        "log_file_created": "2025-10-23T17:44:31Z"
      }
    },
    {
      "description": "(S) TRANSMITTED TO (H)",
      "date": "2025-03-17",
      "organization_id": "~{\"classification\": \"upper\"}",
      "classification": [
        "passage"
      ],
      "related_entities": [],
      "_processing": {
        "log_file_created": "2025-10-23T17:44:31Z"
      }
    },
    {
      "description": "(S) VERSION: SJR 10",
      "date": "2025-03-17",
      "organization_id": "~{\"classification\": \"upper\"}",
      "classification": [],
      "related_entities": [],
      "_processing": {
        "log_file_created": "2025-10-23T17:44:31Z"
      }
    },
    {
      "description": "(H) READ THE FIRST TIME - REFERRALS",
      "date": "2025-03-21",
      "organization_id": "~{\"classification\": \"lower\"}",
      "classification": [
        "reading-1"
      ],
      "related_entities": [],
      "_processing": {
        "log_file_created": "2025-10-23T17:44:31Z"
      }
    },
    {
      "description": "(H) MLV",
      "date": "2025-03-21",
      "organization_id": "~{\"classification\": \"lower\"}",
      "classification": [],
      "related_entities": [],
      "_processing": {
        "log_file_created": "2025-10-23T17:44:31Z"
      }
    },
    {
      "description": "(H) CROSS SPONSOR(S): NELSON",
      "date": "2025-03-21",
      "organization_id": "~{\"classification\": \"lower\"}",
      "classification": [],
      "related_entities": [],
      "_processing": {
        "log_file_created": "2025-10-23T17:44:31Z"
      }
    },
    {
      "description": "(H) MILITARY & VETERANS' AFFAIRS at 10:15 AM BARNES 124",
      "date": "2025-04-01",
      "organization_id": "~{\"classification\": \"lower\"}",
      "classification": [],
      "related_entities": [],
      "_processing": {
        "log_file_created": "2025-10-23T17:44:31Z"
      }
    },
    {
      "description": "(H) Heard & Held",
      "date": "2025-04-01",
      "organization_id": "~{\"classification\": \"lower\"}",
      "classification": [],
      "related_entities": [],
      "_processing": {
        "log_file_created": "2025-10-23T17:44:31Z"
      }
    },
    {
      "description": "(H) MILITARY & VETERANS' AFFAIRS at 10:15 AM BARNES 124",
      "date": "2025-04-03",
      "organization_id": "~{\"classification\": \"lower\"}",
      "classification": [],
      "related_entities": [],
      "_processing": {
        "log_file_created": "2025-10-23T17:44:31Z"
      }
    },
    {
      "description": "(H) -- MEETING CANCELED --",
      "date": "2025-04-03",
      "organization_id": "~{\"classification\": \"lower\"}",
      "classification": [],
      "related_entities": [],
      "_processing": {
        "log_file_created": "2025-10-23T17:44:31Z"
      }
    },
    {
      "description": "(H) MILITARY & VETERANS' AFFAIRS at 10:15 AM BARNES 124",
      "date": "2025-04-08",
      "organization_id": "~{\"classification\": \"lower\"}",
      "classification": [],
      "related_entities": [],
      "_processing": {
        "log_file_created": "2025-10-23T17:44:31Z"
      }
    },
    {
      "description": "(H) Moved SJR 10 Out of Committee",
      "date": "2025-04-08",
      "organization_id": "~{\"classification\": \"lower\"}",
      "classification": [],
      "related_entities": [],
      "_processing": {
        "log_file_created": "2025-10-23T17:44:31Z"
      }
    },
    {
      "description": "(H) MLV RPT 6DP",
      "date": "2025-04-09",
      "organization_id": "~{\"classification\": \"lower\"}",
      "classification": [],
      "related_entities": [],
      "_processing": {
        "log_file_created": "2025-10-23T17:44:31Z"
      }
    },
    {
      "description": "(H) DP: SADDLER, HALL, NELSON, GRAY, ALLARD, EISCHEID",
      "date": "2025-04-09",
      "organization_id": "~{\"classification\": \"lower\"}",
      "classification": [],
      "related_entities": [],
      "_processing": {
        "log_file_created": "2025-10-23T17:44:31Z"
      }
    },
    {
      "description": "(H) FN1: ZERO(LEG)",
      "date": "2025-04-09",
      "organization_id": "~{\"classification\": \"lower\"}",
      "classification": [],
      "related_entities": [],
      "_processing": {
        "log_file_created": "2025-10-23T17:44:31Z"
      }
    },
    {
      "description": "(H) CROSS SPONSOR(S): SCHRAGE",
      "date": "2025-04-11",
      "organization_id": "~{\"classification\": \"lower\"}",
      "classification": [],
      "related_entities": [],
      "_processing": {
        "log_file_created": "2025-10-23T17:44:31Z"
      }
    },
    {
      "description": "(H) RULES TO CALENDAR 4/28/2025",
      "date": "2025-04-28",
      "organization_id": "~{\"classification\": \"lower\"}",
      "classification": [],
      "related_entities": [],
      "_processing": {
        "log_file_created": "2025-10-23T17:44:31Z"
      }
    },
    {
      "description": "(H) READ THE SECOND TIME",
      "date": "2025-04-28",
      "organization_id": "~{\"classification\": \"lower\"}",
      "classification": [
        "reading-2"
      ],
      "related_entities": [],
      "_processing": {
        "log_file_created": "2025-10-23T17:44:31Z"
      }
    },
    {
      "description": "(H) AM NO 1 OFFERED AND WITHDRAWN",
      "date": "2025-04-28",
      "organization_id": "~{\"classification\": \"lower\"}",
      "classification": [],
      "related_entities": [],
      "_processing": {
        "log_file_created": "2025-10-23T17:44:31Z"
      }
    },
    {
      "description": "(H) AM NO 2 ADOPTED UC",
      "date": "2025-04-28",
      "organization_id": "~{\"classification\": \"lower\"}",
      "classification": [
        "amendment-passage"
      ],
      "related_entities": [],
      "_processing": {
        "log_file_created": "2025-10-23T17:44:31Z"
      }
    },
    {
      "description": "(H) ADVANCED TO THIRD READING 4/30 CALENDAR",
      "date": "2025-04-28",
      "organization_id": "~{\"classification\": \"lower\"}",
      "classification": [
        "reading-3"
      ],
      "related_entities": [],
      "_processing": {
        "log_file_created": "2025-10-23T17:44:31Z"
      }
    },
    {
      "description": "(H) CROSS SPONSOR(S): GALVIN, JOSEPHSON, EISCHEID",
      "date": "2025-04-28",
      "organization_id": "~{\"classification\": \"lower\"}",
      "classification": [],
      "related_entities": [],
      "_processing": {
        "log_file_created": "2025-10-23T17:44:31Z"
      }
    },
    {
      "description": "(H) READ THE THIRD TIME SJR 10 AM H",
      "date": "2025-04-30",
      "organization_id": "~{\"classification\": \"lower\"}",
      "classification": [
        "reading-3"
      ],
      "related_entities": [],
      "_processing": {
        "log_file_created": "2025-10-23T17:44:31Z"
      }
    },
    {
      "description": "(H) PASSED Y39 E1",
      "date": "2025-04-30",
      "organization_id": "~{\"classification\": \"lower\"}",
      "classification": [
        "passage"
      ],
      "related_entities": [],
      "_processing": {
        "log_file_created": "2025-10-23T17:44:31Z"
      }
    },
    {
      "description": "(H) COSTELLO NOTICE OF RECONSIDERATION",
      "date": "2025-04-30",
      "organization_id": "~{\"classification\": \"lower\"}",
      "classification": [],
      "related_entities": [],
      "_processing": {
        "log_file_created": "2025-10-23T17:44:31Z"
      }
    },
    {
      "description": "(H) CROSS SPONSOR(S): GRAY, KOPP, STORY, MINA",
      "date": "2025-04-30",
      "organization_id": "~{\"classification\": \"lower\"}",
      "classification": [],
      "related_entities": [],
      "_processing": {
        "log_file_created": "2025-10-23T17:44:31Z"
      }
    },
    {
      "description": "(H) RECONSIDERATION NOT TAKEN UP",
      "date": "2025-05-02",
      "organization_id": "~{\"classification\": \"lower\"}",
      "classification": [],
      "related_entities": [],
      "_processing": {
        "log_file_created": "2025-10-23T17:44:31Z"
      }
    },
    {
      "description": "(H) TRANSMITTED TO (S) AS AMENDED",
      "date": "2025-05-02",
      "organization_id": "~{\"classification\": \"lower\"}",
      "classification": [
        "passage"
      ],
      "related_entities": [],
      "_processing": {
        "log_file_created": "2025-10-23T17:44:31Z"
      }
    },
    {
      "description": "(H) VERSION: SJR 10 AM H",
      "date": "2025-05-02",
      "organization_id": "~{\"classification\": \"lower\"}",
      "classification": [],
      "related_entities": [],
      "_processing": {
        "log_file_created": "2025-10-23T17:44:31Z"
      }
    },
    {
      "description": "(S) CONCUR MESSAGE READ AND TAKEN UP",
      "date": "2025-05-05",
      "organization_id": "~{\"classification\": \"upper\"}",
      "classification": [],
      "related_entities": [],
      "_processing": {
        "log_file_created": "2025-10-23T17:44:31Z"
      }
    },
    {
      "description": "(S) CONCUR AM OF (H) Y19 N- E1",
      "date": "2025-05-05",
      "organization_id": "~{\"classification\": \"upper\"}",
      "classification": [],
      "related_entities": [],
      "_processing": {
        "log_file_created": "2025-10-23T17:44:31Z"
      }
    },
    {
      "description": "(S) 10:30 A.M. 6/20/25 Transmitted to Governor",
      "date": "2025-07-30",
      "organization_id": "~{\"classification\": \"upper\"}",
      "classification": [
        "executive-receipt"
      ],
      "related_entities": [],
      "_processing": {
        "log_file_created": "2025-10-23T17:44:31Z"
      }
    },
    {
      "description": "(S) MANIFEST ERROR(S)",
      "date": "2025-07-30",
      "organization_id": "~{\"classification\": \"upper\"}",
      "classification": [],
      "related_entities": [],
      "_processing": {
        "log_file_created": "2025-10-23T17:44:31Z"
      }
    },
    {
      "description": "(S) PERMANENTLY FILED 7/16 LEGIS RESOLVE 4",
      "date": "2025-07-30",
      "organization_id": "~{\"classification\": \"upper\"}",
      "classification": [],
      "related_entities": [],
      "_processing": {
        "log_file_created": "2025-10-23T17:44:31Z"
      }
    }
  ],
  "sponsorships": [
    {
      "name": "Wielechowski",
      "classification": "primary",
      "entity_type": "person",
      "primary": true,
      "person_id": "~{\"chamber\": \"upper\", \"name\": \"Wielechowski\"}",
      "organization_id": null
    },
    {
      "name": "Gray-Jackson",
      "classification": "cosponsor",
      "entity_type": "person",
      "primary": false,
      "person_id": "~{\"chamber\": \"upper\", \"name\": \"Gray-Jackson\"}",
      "organization_id": null
    },
    {
      "name": "Kawasaki",
      "classification": "cosponsor",
      "entity_type": "person",
      "primary": false,
      "person_id": "~{\"chamber\": \"upper\", \"name\": \"Kawasaki\"}",
      "organization_id": null
    },
    {
      "name": "Dunbar",
      "classification": "cosponsor",
      "entity_type": "person",
      "primary": false,
      "person_id": "~{\"chamber\": \"upper\", \"name\": \"Dunbar\"}",
      "organization_id": null
    },
    {
      "name": "Tobin",
      "classification": "cosponsor",
      "entity_type": "person",
      "primary": false,
      "person_id": "~{\"chamber\": \"upper\", \"name\": \"Tobin\"}",
      "organization_id": null
    },
    {
      "name": "Nelson",
      "classification": "cosponsor",
      "entity_type": "person",
      "primary": false,
      "person_id": "~{\"chamber\": \"lower\", \"name\": \"Nelson\"}",
      "organization_id": null
    },
    {
      "name": "Schrage",
      "classification": "cosponsor",
      "entity_type": "person",
      "primary": false,
      "person_id": "~{\"chamber\": \"lower\", \"name\": \"Schrage\"}",
      "organization_id": null
    },
    {
      "name": "Galvin",
      "classification": "cosponsor",
      "entity_type": "person",
      "primary": false,
      "person_id": "~{\"chamber\": \"lower\", \"name\": \"Galvin\"}",
      "organization_id": null
    },
    {
      "name": "Josephson",
      "classification": "cosponsor",
      "entity_type": "person",
      "primary": false,
      "person_id": "~{\"chamber\": \"lower\", \"name\": \"Josephson\"}",
      "organization_id": null
    },
    {
      "name": "Eischeid",
      "classification": "cosponsor",
      "entity_type": "person",
      "primary": false,
      "person_id": "~{\"chamber\": \"lower\", \"name\": \"Eischeid\"}",
      "organization_id": null
    },
    {
      "name": "Gray",
      "classification": "cosponsor",
      "entity_type": "person",
      "primary": false,
      "person_id": "~{\"chamber\": \"lower\", \"name\": \"Gray\"}",
      "organization_id": null
    },
    {
      "name": "Kopp",
      "classification": "cosponsor",
      "entity_type": "person",
      "primary": false,
      "person_id": "~{\"chamber\": \"lower\", \"name\": \"Kopp\"}",
      "organization_id": null
    },
    {
      "name": "Story",
      "classification": "cosponsor",
      "entity_type": "person",
      "primary": false,
      "person_id": "~{\"chamber\": \"lower\", \"name\": \"Story\"}",
      "organization_id": null
    },
    {
      "name": "Mina",
      "classification": "cosponsor",
      "entity_type": "person",
      "primary": false,
      "person_id": "~{\"chamber\": \"lower\", \"name\": \"Mina\"}",
      "organization_id": null
    }
  ],
  "related_bills": [],
  "versions": [
    {
      "note": "SJR 10",
      "links": [
        {
          "url": "https://www.akleg.gov/basis/Bill/Text/34?Hsid=SJR010A",
          "media_type": "text/html"
        },
        {
          "url": "https://www.akleg.gov/PDF/34/Bills/SJR010A.PDF",
          "media_type": "application/pdf"
        }
      ],
      "date": "",
      "classification": ""
    },
    {
      "note": "SJR 10 am H",
      "links": [
        {
          "url": "https://www.akleg.gov/basis/Bill/Text/34?Hsid=SJR010B",
          "media_type": "text/html"
        },
        {
          "url": "https://www.akleg.gov/PDF/34/Bills/SJR010B.PDF",
          "media_type": "application/pdf"
        }
      ],
      "date": "",
      "classification": ""
    },
    {
      "note": "Enrolled SJR 10",
      "links": [
        {
          "url": "https://www.akleg.gov/basis/Bill/Text/34?Hsid=SJR010Z",
          "media_type": "text/html"
        },
        {
          "url": "https://www.akleg.gov/PDF/34/Bills/SJR010Z.PDF",
          "media_type": "application/pdf"
        }
      ],
      "date": "",
      "classification": ""
    }
  ],
  "documents": [
    {
      "note": "Sponsor Statement",
      "links": [
        {
          "url": "http://www.akleg.gov/basis/get_documents.asp?session=34&docid=4266",
          "media_type": "pdf"
        }
      ],
      "date": "",
      "classification": ""
    },
    {
      "note": "SJR 10 Zero Fiscal Note",
      "links": [
        {
          "url": "https://www.akleg.gov/basis/get_documents.asp?session=34&docid=4967",
          "media_type": "pdf"
        }
      ],
      "date": "",
      "classification": ""
    },
    {
      "note": "SJR 10 Sponsor Statement 04.01.2025",
      "links": [
        {
          "url": "https://www.akleg.gov/basis/get_documents.asp?session=34&docid=4266",
          "media_type": "pdf"
        }
      ],
      "date": "",
      "classification": ""
    },
    {
      "note": "SJR 10 Presentation 04.01.2025",
      "links": [
        {
          "url": "https://www.akleg.gov/basis/get_documents.asp?session=34&docid=4265",
          "media_type": "pdf"
        }
      ],
      "date": "",
      "classification": ""
    },
    {
      "note": "SJR010A",
      "links": [
        {
          "url": "https://www.akleg.gov/basis/get_documents.asp?session=34&docid=4264",
          "media_type": "pdf"
        },
        {
          "url": "https://www.akleg.gov/basis/get_documents.asp?session=34&docid=1836",
          "media_type": "pdf"
        }
      ],
      "date": "",
      "classification": ""
    },
    {
      "note": "SJR 10 Letters of Support to SSTA 3.21.2025",
      "links": [
        {
          "url": "https://www.akleg.gov/basis/get_documents.asp?session=34&docid=4262",
          "media_type": "pdf"
        }
      ],
      "date": "",
      "classification": ""
    },
    {
      "note": "SJR 10 letters of support",
      "links": [
        {
          "url": "https://www.akleg.gov/basis/get_documents.asp?session=34&docid=2209",
          "media_type": "pdf"
        }
      ],
      "date": "",
      "classification": ""
    },
    {
      "note": "SJR10-LEG-SESS-02-24-2025",
      "links": [
        {
          "url": "https://www.akleg.gov/basis/get_documents.asp?session=34&docid=1922",
          "media_type": "pdf"
        }
      ],
      "date": "",
      "classification": ""
    }
  ],
  "citations": [],
  "sources": [
    {
      "url": "https://www.akleg.gov/basis/Bill/Detail/34?Root=SJR10",
      "note": ""
    },
    {
      "url": "https://www.akleg.gov/basis/Bill/Detail/34?Root=SJR10#tab5_4",
      "note": ""
    }
  ],
  "extras": {},
  "jurisdiction": {
    "id": "ocd-jurisdiction/country:us/state:ak/government",
    "name": "Alaska",
    "classification": "state",
    "division_id": "ocd-division/country:us/state:ak"
  },
  "_processing": {
    "logs_latest_update": "2025-10-23T17:44:31Z",
    "text_extraction_latest_update": "2025-10-23T18:12:59.750283Z"
  }
}