{
  "legislative_session": "34",
  "identifier": "HB1",
  "title": "An Act relating to specie as legal tender in the state; and relating to borough and city sales and use taxes on specie.",
  "from_organization": "~{\"classification\": \"lower\"}",
  "classification": [
    "bill"
  ],
  "subject": [
    "DEBT",
    "FINANCE",
    "LEGISLATIVE COMMITTEES",
    "MUNICIPALITIES",
    "SALES",
    "TAXATION"
  ],
  "abstracts": [],
  "other_titles": [],
  "other_identifiers": [],
  "actions": [
    {
      "description": "(H) Prefile released 1/10/25",
      "date": "2025-01-22",
      "organization_id": "~{\"classification\": \"lower\"}",
      "classification": [
        "filing"
      ],
      "related_entities": [],
      "_processing": {
        "log_file_created": "2025-10-23T17:44:30Z"
      }
    },
    {
      "description": "(H) READ THE FIRST TIME - REFERRALS",
      "date": "2025-01-22",
      "organization_id": "~{\"classification\": \"lower\"}",
      "classification": [
        "reading-1"
      ],
      "related_entities": [],
      "_processing": {
        "log_file_created": "2025-10-23T17:44:30Z"
      }
    },
    {
      "description": "(H) STA, FIN",
      "date": "2025-01-22",
      "organization_id": "~{\"classification\": \"lower\"}",
      "classification": [],
      "related_entities": [],
      "_processing": {
        "log_file_created": "2025-10-23T17:44:30Z"
      }
    },
    {
      "description": "(H) COSPONSOR(S): RAUSCHER",
      "date": "2025-01-31",
      "organization_id": "~{\"classification\": \"lower\"}",
      "classification": [],
      "related_entities": [],
      "_processing": {
        "log_file_created": "2025-10-23T17:44:30Z"
      }
    },
    {
      "description": "(H) STATE AFFAIRS at 03:15 PM GRUENBERG 120",
      "date": "2025-04-15",
      "organization_id": "~{\"classification\": \"lower\"}",
      "classification": [],
      "related_entities": [],
      "_processing": {
        "log_file_created": "2025-10-23T17:44:30Z"
      }
    },
    {
      "description": "(H) -- MEETING CANCELED --",
      "date": "2025-04-15",
      "organization_id": "~{\"classification\": \"lower\"}",
      "classification": [],
      "related_entities": [],
      "_processing": {
        "log_file_created": "2025-10-23T17:44:30Z"
      }
    },
    {
      "description": "(H) COSPONSOR(S): MOORE",
      "date": "2025-04-28",
      "organization_id": "~{\"classification\": \"lower\"}",
      "classification": [],
      "related_entities": [],
      "_processing": {
        "log_file_created": "2025-10-23T17:44:30Z"
      }
    },
    {
      "description": "(H) STATE AFFAIRS at 03:15 PM GRUENBERG 120",
      "date": "2025-04-29",
      "organization_id": "~{\"classification\": \"lower\"}",
      "classification": [],
      "related_entities": [],
      "_processing": {
        "log_file_created": "2025-10-23T17:44:30Z"
      }
    },
    {
      "description": "(H) Heard & Held",
      "date": "2025-04-29",
      "organization_id": "~{\"classification\": \"lower\"}",
      "classification": [],
      "related_entities": [],
      "_processing": {
        "log_file_created": "2025-10-23T17:44:30Z"
      }
    },
    {
      "description": "(H) COSPONSOR(S): STAPP, TILTON, ALLARD, TOMASZEWSKI, PRAX, COULOMBE, RUFFRIDGE",
      "date": "2025-04-30",
      "organization_id": "~{\"classification\": \"lower\"}",
      "classification": [],
      "related_entities": [],
      "_processing": {
        "log_file_created": "2025-10-23T17:44:30Z"
      }
    },
    {
      "description": "(H) COSPONSOR(S): ELAM, BYNUM",
      "date": "2025-05-02",
      "organization_id": "~{\"classification\": \"lower\"}",
      "classification": [],
      "related_entities": [],
      "_processing": {
        "log_file_created": "2025-10-23T17:44:30Z"
      }
    },
    {
      "description": "(H) COSPONSOR(S): JIMMIE, STUTES",
      "date": "2025-05-07",
      "organization_id": "~{\"classification\": \"lower\"}",
      "classification": [],
      "related_entities": [],
      "_processing": {
        "log_file_created": "2025-10-23T17:44:30Z"
      }
    },
    {
      "description": "(H) STATE AFFAIRS at 03:15 PM GRUENBERG 120",
      "date": "2025-05-08",
      "organization_id": "~{\"classification\": \"lower\"}",
      "classification": [],
      "related_entities": [],
      "_processing": {
        "log_file_created": "2025-10-23T17:44:30Z"
      }
    },
    {
      "description": "(H) Heard & Held",
      "date": "2025-05-08",
      "organization_id": "~{\"classification\": \"lower\"}",
      "classification": [],
      "related_entities": [],
      "_processing": {
        "log_file_created": "2025-10-23T17:44:30Z"
      }
    },
    {
      "description": "(H) STATE AFFAIRS at 03:15 PM GRUENBERG 120",
      "date": "2025-05-15",
      "organization_id": "~{\"classification\": \"lower\"}",
      "classification": [],
      "related_entities": [],
      "_processing": {
        "log_file_created": "2025-10-23T17:44:30Z"
      }
    },
    {
      "description": "(H) Heard & Held -- Delayed to 4:15 pm--",
      "date": "2025-05-15",
      "organization_id": "~{\"classification\": \"lower\"}",
      "classification": [],
      "related_entities": [],
      "_processing": {
        "log_file_created": "2025-10-23T17:44:30Z"
      }
    },
    {
      "description": "(H) STATE AFFAIRS at 01:00 PM GRUENBERG 120",
      "date": "2025-05-17",
      "organization_id": "~{\"classification\": \"lower\"}",
      "classification": [],
      "related_entities": [],
      "_processing": {
        "log_file_created": "2025-10-23T17:44:30Z"
      }
    },
    {
      "description": "(H) Moved CSHB 1(STA) Out of Committee -- Delayed to 15 min Following Session --",
      "date": "2025-05-17",
      "organization_id": "~{\"classification\": \"lower\"}",
      "classification": [],
      "related_entities": [],
      "_processing": {
        "log_file_created": "2025-10-23T17:44:30Z"
      }
    },
    {
      "description": "(H) STA RPT CS(STA) 6DP 1NR",
      "date": "2025-05-18",
      "organization_id": "~{\"classification\": \"lower\"}",
      "classification": [],
      "related_entities": [],
      "_processing": {
        "log_file_created": "2025-10-23T17:44:30Z"
      }
    },
    {
      "description": "(H) DP: VANCE, MCCABE, MOORE, HOLLAND, HIMSCHOOT, CARRICK",
      "date": "2025-05-18",
      "organization_id": "~{\"classification\": \"lower\"}",
      "classification": [],
      "related_entities": [],
      "_processing": {
        "log_file_created": "2025-10-23T17:44:30Z"
      }
    },
    {
      "description": "(H) NR: STORY",
      "date": "2025-05-18",
      "organization_id": "~{\"classification\": \"lower\"}",
      "classification": [],
      "related_entities": [],
      "_processing": {
        "log_file_created": "2025-10-23T17:44:30Z"
      }
    },
    {
      "description": "(H) FN1: ZERO(ADM)",
      "date": "2025-05-18",
      "organization_id": "~{\"classification\": \"lower\"}",
      "classification": [],
      "related_entities": [],
      "_processing": {
        "log_file_created": "2025-10-23T17:44:30Z"
      }
    },
    {
      "description": "(H) FN2: ZERO(CED)",
      "date": "2025-05-18",
      "organization_id": "~{\"classification\": \"lower\"}",
      "classification": [],
      "related_entities": [],
      "_processing": {
        "log_file_created": "2025-10-23T17:44:30Z"
      }
    },
    {
      "description": "(H) REFERRED TO FINANCE",
      "date": "2025-05-18",
      "organization_id": "~{\"classification\": \"lower\"}",
      "classification": [
        "referral-committee"
      ],
      "related_entities": [],
      "_processing": {
        "log_file_created": "2025-10-23T17:44:30Z"
      }
    },
    {
      "description": "(H) COSPONSOR REMOVED: JIMMIE",
      "date": "2025-05-18",
      "organization_id": "~{\"classification\": \"lower\"}",
      "classification": [],
      "related_entities": [],
      "_processing": {
        "log_file_created": "2025-10-23T17:44:30Z"
      }
    }
  ],
  "sponsorships": [
    {
      "name": "Mccabe",
      "classification": "primary",
      "entity_type": "person",
      "primary": true,
      "person_id": "~{\"chamber\": \"lower\", \"name\": \"Mccabe\"}",
      "organization_id": null
    },
    {
      "name": "Underwood",
      "classification": "cosponsor",
      "entity_type": "person",
      "primary": false,
      "person_id": "~{\"chamber\": \"lower\", \"name\": \"Underwood\"}",
      "organization_id": null
    },
    {
      "name": "Johnson",
      "classification": "cosponsor",
      "entity_type": "person",
      "primary": false,
      "person_id": "~{\"chamber\": \"lower\", \"name\": \"Johnson\"}",
      "organization_id": null
    },
    {
      "name": "Rauscher",
      "classification": "cosponsor",
      "entity_type": "person",
      "primary": false,
      "person_id": "~{\"chamber\": \"lower\", \"name\": \"Rauscher\"}",
      "organization_id": null
    },
    {
      "name": "Moore",
      "classification": "cosponsor",
      "entity_type": "person",
      "primary": false,
      "person_id": "~{\"chamber\": \"lower\", \"name\": \"Moore\"}",
      "organization_id": null
    },
    {
      "name": "Stapp",
      "classification": "cosponsor",
      "entity_type": "person",
      "primary": false,
      "person_id": "~{\"chamber\": \"lower\", \"name\": \"Stapp\"}",
      "organization_id": null
    },
    {
      "name": "Tilton",
      "classification": "cosponsor",
      "entity_type": "person",
      "primary": false,
      "person_id": "~{\"chamber\": \"lower\", \"name\": \"Tilton\"}",
      "organization_id": null
    },
    {
      "name": "Allard",
      "classification": "cosponsor",
      "entity_type": "person",
      "primary": false,
      "person_id": "~{\"chamber\": \"lower\", \"name\": \"Allard\"}",
      "organization_id": null
    },
    {
      "name": "Tomaszewski",
      "classification": "cosponsor",
      "entity_type": "person",
      "primary": false,
      "person_id": "~{\"chamber\": \"lower\", \"name\": \"Tomaszewski\"}",
      "organization_id": null
    },
    {
      "name": "Prax",
      "classification": "cosponsor",
      "entity_type": "person",
      "primary": false,
      "person_id": "~{\"chamber\": \"lower\", \"name\": \"Prax\"}",
      "organization_id": null
    },
    {
      "name": "Coulombe",
      "classification": "cosponsor",
      "entity_type": "person",
      "primary": false,
      "person_id": "~{\"chamber\": \"lower\", \"name\": \"Coulombe\"}",
      "organization_id": null
    },
    {
      "name": "Ruffridge",
      "classification": "cosponsor",
      "entity_type": "person",
      "primary": false,
      "person_id": "~{\"chamber\": \"lower\", \"name\": \"Ruffridge\"}",
      "organization_id": null
    },
    {
      "name": "Elam",
      "classification": "cosponsor",
      "entity_type": "person",
      "primary": false,
      "person_id": "~{\"chamber\": \"lower\", \"name\": \"Elam\"}",
      "organization_id": null
    },
    {
      "name": "Bynum",
      "classification": "cosponsor",
      "entity_type": "person",
      "primary": false,
      "person_id": "~{\"chamber\": \"lower\", \"name\": \"Bynum\"}",
      "organization_id": null
    },
    {
      "name": "Stutes",
      "classification": "cosponsor",
      "entity_type": "person",
      "primary": false,
      "person_id": "~{\"chamber\": \"lower\", \"name\": \"Stutes\"}",
      "organization_id": null
    }
  ],
  "related_bills": [],
  "versions": [
    {
      "note": "HB 1",
      "links": [
        {
          "url": "https://www.akleg.gov/basis/Bill/Text/34?Hsid=HB0001A",
          "media_type": "text/html"
        },
        {
          "url": "https://www.akleg.gov/PDF/34/Bills/HB0001A.PDF",
          "media_type": "application/pdf"
        }
      ],
      "date": "",
      "classification": ""
    },
    {
      "note": "CSHB 1(STA)",
      "links": [
        {
          "url": "https://www.akleg.gov/basis/Bill/Text/34?Hsid=HB0001B",
          "media_type": "text/html"
        },
        {
          "url": "https://www.akleg.gov/PDF/34/Bills/HB0001B.PDF",
          "media_type": "application/pdf"
        }
      ],
      "date": "",
      "classification": ""
    }
  ],
  "documents": [
    {
      "note": "Sponsor Statement",
      "links": [
        {
          "url": "http://www.akleg.gov/basis/get_documents.asp?session=34&docid=5519",
          "media_type": "pdf"
        }
      ],
      "date": "",
      "classification": ""
    },
    {
      "note": "HB1 RepMcCabe Response to Andressen.5.16.25",
      "links": [
        {
          "url": "https://www.akleg.gov/basis/get_documents.asp?session=34&docid=8143",
          "media_type": "pdf"
        }
      ],
      "date": "",
      "classification": ""
    },
    {
      "note": "HB 1 Conceptual Amendment 3",
      "links": [
        {
          "url": "https://www.akleg.gov/basis/get_documents.asp?session=34&docid=8139",
          "media_type": "pdf"
        }
      ],
      "date": "",
      "classification": ""
    },
    {
      "note": "HB 1 Legal Memo Re. Definition of Person",
      "links": [
        {
          "url": "https://www.akleg.gov/basis/get_documents.asp?session=34&docid=8138",
          "media_type": "pdf"
        }
      ],
      "date": "",
      "classification": ""
    },
    {
      "note": "HB 1 Citizens For Sound Money Follow Up 5-16-25",
      "links": [
        {
          "url": "https://www.akleg.gov/basis/get_documents.asp?session=34&docid=8114",
          "media_type": "pdf"
        }
      ],
      "date": "",
      "classification": ""
    },
    {
      "note": "HB 1 Testimony Nils Andreassen 5-15-25",
      "links": [
        {
          "url": "https://www.akleg.gov/basis/get_documents.asp?session=34&docid=8080",
          "media_type": "pdf"
        }
      ],
      "date": "",
      "classification": ""
    },
    {
      "note": "HB 1 Amendment 2 HSTA",
      "links": [
        {
          "url": "https://www.akleg.gov/basis/get_documents.asp?session=34&docid=8033",
          "media_type": "pdf"
        }
      ],
      "date": "",
      "classification": ""
    },
    {
      "note": "HB 1 Written Testimony Rec'd 5-14-25",
      "links": [
        {
          "url": "https://www.akleg.gov/basis/get_documents.asp?session=34&docid=7868",
          "media_type": "pdf"
        }
      ],
      "date": "",
      "classification": ""
    },
    {
      "note": "HB 1 Amendment 1 HSTA",
      "links": [
        {
          "url": "https://www.akleg.gov/basis/get_documents.asp?session=34&docid=7859",
          "media_type": "pdf"
        }
      ],
      "date": "",
      "classification": ""
    },
    {
      "note": "HB 1 Written Testimony Rec'd 5-13-25",
      "links": [
        {
          "url": "https://www.akleg.gov/basis/get_documents.asp?session=34&docid=7740",
          "media_type": "pdf"
        }
      ],
      "date": "",
      "classification": ""
    },
    {
      "note": "HB 1 DCRA Response to HSTA 5.7.25",
      "links": [
        {
          "url": "https://www.akleg.gov/basis/get_documents.asp?session=34&docid=7409",
          "media_type": "pdf"
        }
      ],
      "date": "",
      "classification": ""
    },
    {
      "note": "HB 1 Written Testimony Rec'd 4-29-25",
      "links": [
        {
          "url": "https://www.akleg.gov/basis/get_documents.asp?session=34&docid=7381",
          "media_type": "pdf"
        }
      ],
      "date": "",
      "classification": ""
    },
    {
      "note": "HB 1 Written Testimony Rec'd 4-28-25",
      "links": [
        {
          "url": "https://www.akleg.gov/basis/get_documents.asp?session=34&docid=6539",
          "media_type": "pdf"
        }
      ],
      "date": "",
      "classification": ""
    },
    {
      "note": "HB1.VerA.Supporting Emails from 2024.3.20.25",
      "links": [
        {
          "url": "https://www.akleg.gov/basis/get_documents.asp?session=34&docid=5526",
          "media_type": "pdf"
        }
      ],
      "date": "",
      "classification": ""
    },
    {
      "note": "HB1.VerA..informational Documents.3.20.25",
      "links": [
        {
          "url": "https://www.akleg.gov/basis/get_documents.asp?session=34&docid=5525",
          "media_type": "pdf"
        }
      ],
      "date": "",
      "classification": ""
    },
    {
      "note": "HB1.VerA.SoundMoneySupportLtr.3.20.25",
      "links": [
        {
          "url": "https://www.akleg.gov/basis/get_documents.asp?session=34&docid=5524",
          "media_type": "pdf"
        }
      ],
      "date": "",
      "classification": ""
    },
    {
      "note": "HB 1 Fiscal Note DCCED-DCRA-04-11-25",
      "links": [
        {
          "url": "https://www.akleg.gov/basis/get_documents.asp?session=34&docid=5523",
          "media_type": "pdf"
        }
      ],
      "date": "",
      "classification": ""
    },
    {
      "note": "HB 1 Fiscal Note DOA-DOF-4-11-25",
      "links": [
        {
          "url": "https://www.akleg.gov/basis/get_documents.asp?session=34&docid=5522",
          "media_type": "pdf"
        }
      ],
      "date": "",
      "classification": ""
    },
    {
      "note": "HB1.VerA.Sectional Analysis.3.20.25",
      "links": [
        {
          "url": "https://www.akleg.gov/basis/get_documents.asp?session=34&docid=5521",
          "media_type": "pdf"
        }
      ],
      "date": "",
      "classification": ""
    },
    {
      "note": "HB1.VerA.3.20.25",
      "links": [
        {
          "url": "https://www.akleg.gov/basis/get_documents.asp?session=34&docid=5520",
          "media_type": "pdf"
        }
      ],
      "date": "",
      "classification": ""
    },
    {
      "note": "HB1.VerA.SponsorStatement.3.20.25",
      "links": [
        {
          "url": "https://www.akleg.gov/basis/get_documents.asp?session=34&docid=5519",
          "media_type": "pdf"
        }
      ],
      "date": "",
      "classification": ""
    }
  ],
  "citations": [],
  "sources": [
    {
      "url": "https://www.akleg.gov/basis/Bill/Detail/34?Root=HB1",
      "note": ""
    },
    {
      "url": "https://www.akleg.gov/basis/Bill/Detail/34?Root=HB1#tab5_4",
      "note": ""
    }
  ],
  "extras": {},
  "jurisdiction": {
    "id": "ocd-jurisdiction/country:us/state:ak/government",
    "name": "Alaska",
    "classification": "state",
    "division_id": "ocd-division/country:us/state:ak"
  },
  "_processing": {
    "logs_latest_update": "2025-10-23T17:44:30Z",
    "text_extraction_latest_update": "2025-10-23T18:08:02.361184Z"
  }
}