{
  "identifier": "",
  "motion_text": "(H) PASSED Y39 E1 #1241",
  "motion_classification": [
    "passage"
  ],
  "start_date": "2025-05-16",
  "result": "pass",
  "organization": "~{\"classification\": \"lower\"}",
  "legislative_session": "34",
  "bill": "e5d37d7c-b036-11f0-9986-42809aea841e",
  "bill_action": null,
  "bill_identifier": "HB23",
  "votes": [],
  "counts": [
    {
      "option": "yes",
      "value": 39
    },
    {
      "option": "no",
      "value": 0
    },
    {
      "option": "other",
      "value": 1
    }
  ],
  "sources": [
    {
      "url": "https://www.akleg.gov/basis/Journal/Pages/34?Chamber=H&Bill=HB23&Page=01241#1241",
      "note": ""
    }
  ],
  "extras": {}
}